countryflag/__init__.py
countryflag/__main__.py
countryflag/lookup.py
countryflag/py.typed
countryflag/cache/__init__.py
countryflag/cache/base.py
countryflag/cache/disk.py
countryflag/cache/memory.py
countryflag/cli/__init__.py
countryflag/cli/main.py
countryflag/core/__init__.py
countryflag/core/converters.py
countryflag/core/exceptions.py
countryflag/core/flag.py
countryflag/core/models.py
countryflag/plugins/__init__.py
countryflag/plugins/base.py
countryflag/utils/__init__.py
countryflag/utils/io.py
countryflag/utils/text.py
countryflag/utils/validation.py
countryflag-1.1.0.dist-info/licenses/LICENSE
countryflag-1.1.0.dist-info/METADATA
countryflag-1.1.0.dist-info/WHEEL
countryflag-1.1.0.dist-info/entry_points.txt
countryflag-1.1.0.dist-info/top_level.txt
countryflag-1.1.0.dist-info/RECORD
