Metadata-Version: 2.4
Name: countryflag
Version: 1.1.0
Summary: A Python package for converting country names into emoji flags
Home-page: https://github.com/lendersmark/countryflag
Author: Lendersmark
Author-email: Lendersmark <author@example.com>
License: MIT
Project-URL: Homepage, https://github.com/lendersmark/countryflag
Project-URL: Bug Tracker, https://github.com/lendersmark/countryflag/issues
Project-URL: Documentation, https://countryflag.readthedocs.io/
Classifier: Development Status :: 5 - Production/Stable
Classifier: Programming Language :: Python :: 3
Classifier: Programming Language :: Python :: 3.9
Classifier: Programming Language :: Python :: 3.10
Classifier: Programming Language :: Python :: 3.11
Classifier: Programming Language :: Python :: 3.12
Classifier: Operating System :: OS Independent
Classifier: Topic :: Software Development :: Libraries :: Python Modules
Classifier: Topic :: Text Processing
Classifier: Intended Audience :: Developers
Requires-Python: >=3.9
License-File: LICENSE
Requires-Dist: emoji-country-flag
Requires-Dist: country_converter
Requires-Dist: typeguard
Requires-Dist: prompt_toolkit
Requires-Dist: aioconsole
Provides-Extra: dev
Requires-Dist: black; extra == "dev"
Requires-Dist: isort; extra == "dev"
Requires-Dist: mypy; extra == "dev"
Requires-Dist: pytest; extra == "dev"
Requires-Dist: pytest-cov; extra == "dev"
Requires-Dist: tox; extra == "dev"
Requires-Dist: pre-commit; extra == "dev"
Requires-Dist: sphinx; extra == "dev"
Requires-Dist: sphinx-rtd-theme; extra == "dev"
Requires-Dist: hypothesis; extra == "dev"
Requires-Dist: flake8; extra == "dev"
Requires-Dist: flake8-docstrings; extra == "dev"
Requires-Dist: flake8-comprehensions; extra == "dev"
Requires-Dist: flake8-bugbear; extra == "dev"
Requires-Dist: flake8-annotations; extra == "dev"
Provides-Extra: test
Requires-Dist: pytest; extra == "test"
Requires-Dist: pytest-cov; extra == "test"
Requires-Dist: pytest-benchmark; extra == "test"
Requires-Dist: hypothesis; extra == "test"
Requires-Dist: psutil; extra == "test"
Requires-Dist: cli_test_helpers; extra == "test"
Provides-Extra: docs
Requires-Dist: sphinx; extra == "docs"
Requires-Dist: sphinx-rtd-theme; extra == "docs"
Dynamic: author
Dynamic: home-page
Dynamic: license-file
Dynamic: requires-python
